daac/__init__.py
daac/p1.py
daac/p2.py
daac/p3.py
daac/p4.py
daac/p5.py
daac/p6.py
daac/p7.py
daac/program.py
daac/programs.py
daac-1.0.dist-info/METADATA
daac-1.0.dist-info/WHEEL
daac-1.0.dist-info/entry_points.txt
daac-1.0.dist-info/top_level.txt
daac-1.0.dist-info/RECORD
