Metadata-Version: 2.1
Name: daac
Version: 1.0
Summary: A package to echo contents of programs.py to clipboard
Author: Your Name
Author-email: your.email@example.com
Requires-Dist: pyperclip
